togax_xml_layout/__init__.py
togax_xml_layout/xml_parser.py
togax_xml_layout_plugin-0.0.3.dist-info/LICENSE.md
togax_xml_layout_plugin-0.0.3.dist-info/METADATA
togax_xml_layout_plugin-0.0.3.dist-info/WHEEL
togax_xml_layout_plugin-0.0.3.dist-info/top_level.txt
togax_xml_layout_plugin-0.0.3.dist-info/RECORD
