Metadata-Version: 2.1
Name: togax-xml-layout-plugin
Version: 0.0.3
Summary: XML unofficial Toga layout parser
Home-page: https://github.com/sinedie/togax-xml-layout-plugin
Author: EAR
Author-email: sinedie@protonmail.com
License: FREE
Keywords: python,toga,gui,xml,layout
Requires-Python: >=3.6
License-File: LICENSE.md
Requires-Dist: toga
